MANIFEST.in
README.rst
setup.py
cartodbsync/__init__.py
cartodbsync/__init__.pyc
cartodbsync/models.py
cartodbsync/synchronize.py
cartodbsync/synchronizers.py
cartodbsync/__pycache__/__init__.cpython-34.pyc
cartodbsync/__pycache__/models.cpython-34.pyc
cartodbsync/__pycache__/synchronize.cpython-34.pyc
cartodbsync/__pycache__/synchronizers.cpython-34.pyc
cartodbsync/management/__init__.py
cartodbsync/management/__pycache__/__init__.cpython-34.pyc
cartodbsync/management/commands/__init__.py
cartodbsync/management/commands/cartodbsync.py
cartodbsync/management/commands/__pycache__/__init__.cpython-34.pyc
cartodbsync/management/commands/__pycache__/cartodbsync.cpython-34.pyc
cartodbsync/migrations/0001_initial.py
cartodbsync/migrations/__init__.py
cartodbsync/migrations/__pycache__/0001_initial.cpython-34.pyc
cartodbsync/migrations/__pycache__/__init__.cpython-34.pyc
django_cartodb_sync.egg-info/PKG-INFO
django_cartodb_sync.egg-info/SOURCES.txt
django_cartodb_sync.egg-info/dependency_links.txt
django_cartodb_sync.egg-info/pbr.json
django_cartodb_sync.egg-info/requires.txt
django_cartodb_sync.egg-info/top_level.txt