Metadata-Version: 1.1
Name: django-cartodb-sync
Version: 0.3.0
Summary: A Django app that helps keep CartoDB tables synchronized with Django models.
Home-page: https://github.com/ebrelsford/django-cartodb-sync
Author: Eric Brelsford
Author-email: ebrelsford@gmail.com
License: BSD License
Platform: OS Independent
Classifier: Development Status :: 4 - Beta
Classifier: Environment :: Web Environment
Classifier: Framework :: Django
Classifier: Intended Audience :: Developers
Classifier: License :: OSI Approved :: BSD License
Classifier: Operating System :: OS Independent
Classifier: Programming Language :: Python
Classifier: Programming Language :: Python :: 2
Classifier: Programming Language :: Python :: 3
Classifier: Topic :: Internet :: WWW/HTTP :: Dynamic Content
Classifier: Topic :: Software Development
